snakeng/__init__.py
snakeng/__main__.py
snakeng/snake.py
snakeng-2.0.0.dist-info/LICENSE
snakeng-2.0.0.dist-info/METADATA
snakeng-2.0.0.dist-info/WHEEL
snakeng-2.0.0.dist-info/top_level.txt
snakeng-2.0.0.dist-info/RECORD
